pybreak/__init__.py
pybreak/__main__.py
pybreak/pybreak.py
pybreak/repl.py
pybreak/run.py
pybreak-0.1.0.dist-info/entry_points.txt
pybreak-0.1.0.dist-info/WHEEL
pybreak-0.1.0.dist-info/METADATA
pybreak-0.1.0.dist-info/RECORD
