Metadata-Version: 2.1
Name: pybreak
Version: 0.1.0
Summary: pybreak
Author: Darren Burns
Author-email: darren.burns@fanduel.com
Requires-Python: >=3.6
Classifier: Programming Language :: Python :: 3
Classifier: Programming Language :: Python :: 3.6
Classifier: Programming Language :: Python :: 3.7
Classifier: Programming Language :: Python :: 3.8
Requires-Dist: dataclasses (>=0.7,<0.8); python_version == "3.6"
Requires-Dist: prompt-toolkit (>=3.0,<4.0)
